{"stats":{"minecraft:custom/minecraft:time_since_rest":48868,"minecraft:custom/minecraft:leave_game":4,"minecraft:custom/minecraft:play_time":48868,"minecraft:custom/minecraft:time_since_death":48868,"minecraft:custom/minecraft:walk_one_cm":206,"minecraft:custom/minecraft:total_world_time":48868},"stats_source":{"stats":{"minecraft:custom":{"minecraft:time_since_rest":48868,"minecraft:leave_game":4,"minecraft:play_time":48868,"minecraft:time_since_death":48868,"minecraft:walk_one_cm":206,"minecraft:total_world_time":48868}},"DataVersion":2865},"advancements":{"minecraft:recipes/decorations/torch":{"criteria":{"has_stone_pickaxe":"2021-12-27 06:58:18 +0800"},"done":true},"minecraft:story/upgrade_tools":{"criteria":{"stone_pickaxe":"2021-12-27 06:58:18 +0800"},"done":true},"minecraft:adventure/adventuring_time":{"criteria":{"minecraft:forest":"2021-12-27 06:58:18 +0800","minecraft:plains":"2021-12-27 06:58:59 +0800"},"done":false},"DataVersion":2865},"data":{"seen":1640583442700,"time_start":1640559498494,"time_last":1640583442700,"time_lived":2443.2,"playername":"Myuri","names":[{"name":"Myuri"}],"uuid_short":"4ae8f4da320a3d018e0100933ce0922f","lastUpdate":1640620956134,"uuid":"4ae8f4da-320a-3d01-8e01-00933ce0922f","banned":false}}