{"stats":{"minecraft:dropped/minecraft:ender_pearl":7,"minecraft:picked_up/minecraft:golden_carrot":64,"minecraft:picked_up/minecraft:diamond_sword":1,"minecraft:picked_up/minecraft:dragon_head":1,"minecraft:picked_up/minecraft:elytra":1,"minecraft:picked_up/minecraft:emerald":1664,"minecraft:picked_up/minecraft:totem_of_undying":11,"minecraft:picked_up/minecraft:minecart":1,"minecraft:picked_up/minecraft:ender_pearl":156,"minecraft:crafted/minecraft:diamond_sword":1,"minecraft:crafted/minecraft:diamond_helmet":1,"minecraft:crafted/minecraft:diamond_leggings":1,"minecraft:crafted/minecraft:diamond_pickaxe":1,"minecraft:crafted/minecraft:diamond_axe":1,"minecraft:crafted/minecraft:diamond_boots":1,"minecraft:crafted/minecraft:diamond_shovel":1,"minecraft:crafted/minecraft:diamond_chestplate":1,"minecraft:killed/minecraft:enderman":811,"minecraft:used/minecraft:ender_pearl":6,"minecraft:used/minecraft:totem_of_undying":3,"minecraft:used/minecraft:diamond_sword":476,"minecraft:used/minecraft:golden_carrot":13,"minecraft:used/minecraft:potato":7,"minecraft:used/minecraft:dragon_head":1,"minecraft:custom/minecraft:time_since_rest":139771,"minecraft:custom/minecraft:damage_absorbed":80,"minecraft:custom/minecraft:sprint_one_cm":136868,"minecraft:custom/minecraft:open_enderchest":6,"minecraft:custom/minecraft:damage_taken":2715,"minecraft:custom/minecraft:walk_one_cm":121543,"minecraft:custom/minecraft:mob_kills":973,"minecraft:custom/minecraft:drop":1,"minecraft:custom/minecraft:minecart_one_cm":80798,"minecraft:custom/minecraft:damage_dealt":24442,"minecraft:custom/minecraft:traded_with_villager":8,"minecraft:custom/minecraft:swim_one_cm":3800,"minecraft:custom/minecraft:talked_to_villager":30,"minecraft:custom/minecraft:fly_one_cm":803195,"minecraft:custom/minecraft:open_chest":20,"minecraft:custom/minecraft:crouch_one_cm":11422,"minecraft:custom/minecraft:play_time":152952,"minecraft:custom/minecraft:deaths":3,"minecraft:custom/minecraft:sneak_time":4845,"minecraft:custom/minecraft:walk_under_water_one_cm":1966,"minecraft:custom/minecraft:jump":973,"minecraft:custom/minecraft:interact_with_grindstone":2,"minecraft:custom/minecraft:leave_game":6,"minecraft:custom/minecraft:time_since_death":139751,"minecraft:custom/minecraft:walk_on_water_one_cm":3250,"minecraft:custom/minecraft:damage_resisted":55,"minecraft:custom/minecraft:climb_one_cm":495,"minecraft:custom/minecraft:total_world_time":152952,"minecraft:custom/minecraft:fall_one_cm":22793},"stats_source":{"stats":{"minecraft:dropped":{"minecraft:ender_pearl":7},"minecraft:picked_up":{"minecraft:golden_carrot":64,"minecraft:diamond_sword":1,"minecraft:dragon_head":1,"minecraft:elytra":1,"minecraft:emerald":1664,"minecraft:totem_of_undying":11,"minecraft:minecart":1,"minecraft:ender_pearl":156},"minecraft:crafted":{"minecraft:diamond_sword":1,"minecraft:diamond_helmet":1,"minecraft:diamond_leggings":1,"minecraft:diamond_pickaxe":1,"minecraft:diamond_axe":1,"minecraft:diamond_boots":1,"minecraft:diamond_shovel":1,"minecraft:diamond_chestplate":1},"minecraft:killed":{"minecraft:enderman":811},"minecraft:used":{"minecraft:ender_pearl":6,"minecraft:totem_of_undying":3,"minecraft:diamond_sword":476,"minecraft:golden_carrot":13,"minecraft:potato":7,"minecraft:dragon_head":1},"minecraft:custom":{"minecraft:time_since_rest":139771,"minecraft:damage_absorbed":80,"minecraft:sprint_one_cm":136868,"minecraft:open_enderchest":6,"minecraft:damage_taken":2715,"minecraft:walk_one_cm":121543,"minecraft:mob_kills":973,"minecraft:drop":1,"minecraft:minecart_one_cm":80798,"minecraft:damage_dealt":24442,"minecraft:traded_with_villager":8,"minecraft:swim_one_cm":3800,"minecraft:talked_to_villager":30,"minecraft:fly_one_cm":803195,"minecraft:open_chest":20,"minecraft:crouch_one_cm":11422,"minecraft:play_time":152952,"minecraft:deaths":3,"minecraft:sneak_time":4845,"minecraft:walk_under_water_one_cm":1966,"minecraft:jump":973,"minecraft:interact_with_grindstone":2,"minecraft:leave_game":6,"minecraft:time_since_death":139751,"minecraft:walk_on_water_one_cm":3250,"minecraft:damage_resisted":55,"minecraft:climb_one_cm":495,"minecraft:total_world_time":152952,"minecraft:fall_one_cm":22793}},"DataVersion":2865},"advancements":{"minecraft:recipes/misc/iron_nugget_from_blasting":{"criteria":{"has_iron_sword":"2022-01-25 11:01:07 +0800"},"done":true},"minecraft:recipes/transportation/dark_oak_boat":{"criteria":{"in_water":"2022-01-27 19:47:32 +0800"},"done":true},"minecraft:recipes/food/baked_potato_from_smoking":{"criteria":{"has_potato":"2022-01-25 11:00:48 +0800"},"done":true},"minecraft:recipes/building_blocks/emerald_block":{"criteria":{"has_emerald":"2022-01-25 11:24:10 +0800"},"done":true},"minecraft:adventure/kill_a_mob":{"criteria":{"minecraft:enderman":"2022-01-25 11:35:04 +0800"},"done":true},"minecraft:adventure/kill_all_mobs":{"criteria":{"minecraft:enderman":"2022-01-25 11:35:04 +0800"},"done":false},"minecraft:end/root":{"criteria":{"entered_end":"2022-01-25 11:05:48 +0800"},"done":true},"minecraft:story/enter_the_nether":{"criteria":{"entered_nether":"2022-01-25 11:02:37 +0800"},"done":true},"minecraft:story/enter_the_end":{"criteria":{"entered_end":"2022-01-25 11:05:48 +0800"},"done":true},"minecraft:husbandry/balanced_diet":{"criteria":{"potato":"2022-01-25 11:04:08 +0800","golden_carrot":"2022-01-25 11:25:37 +0800"},"done":false},"minecraft:adventure/honey_block_slide":{"criteria":{"honey_block_slide":"2022-01-25 11:08:46 +0800"},"done":true},"minecraft:adventure/trade":{"criteria":{"traded":"2022-01-25 11:27:11 +0800"},"done":true},"minecraft:recipes/transportation/tnt_minecart":{"criteria":{"has_minecart":"2022-01-25 11:05:20 +0800"},"done":true},"minecraft:recipes/food/baked_potato":{"criteria":{"has_potato":"2022-01-25 11:00:48 +0800"},"done":true},"minecraft:recipes/transportation/furnace_minecart":{"criteria":{"has_minecart":"2022-01-25 11:05:20 +0800"},"done":true},"minecraft:nether/root":{"criteria":{"entered_nether":"2022-01-25 11:02:37 +0800"},"done":true},"minecraft:recipes/misc/iron_nugget_from_smelting":{"criteria":{"has_iron_sword":"2022-01-25 11:01:07 +0800"},"done":true},"minecraft:adventure/adventuring_time":{"criteria":{"minecraft:taiga":"2022-01-25 11:05:29 +0800","minecraft:river":"2022-01-27 20:18:20 +0800","minecraft:forest":"2022-01-01 19:51:30 +0800","minecraft:savanna":"2022-01-27 20:15:43 +0800","minecraft:plains":"2022-01-01 19:51:58 +0800"},"done":false},"minecraft:nether/explore_nether":{"criteria":{"minecraft:crimson_forest":"2022-01-25 11:02:37 +0800","minecraft:nether_wastes":"2022-01-25 11:03:50 +0800","minecraft:basalt_deltas":"2022-01-25 11:04:02 +0800"},"done":false},"minecraft:recipes/transportation/chest_minecart":{"criteria":{"has_minecart":"2022-01-25 11:05:20 +0800"},"done":true},"minecraft:recipes/transportation/rail":{"criteria":{"has_minecart":"2022-01-25 11:05:20 +0800"},"done":true},"minecraft:story/iron_tools":{"criteria":{"iron_pickaxe":"2022-01-25 11:01:21 +0800"},"done":true},"minecraft:husbandry/root":{"criteria":{"consumed_item":"2022-01-25 11:04:08 +0800"},"done":true},"minecraft:recipes/transportation/hopper_minecart":{"criteria":{"has_minecart":"2022-01-25 11:05:19 +0800"},"done":true},"minecraft:recipes/decorations/chest":{"criteria":{"has_lots_of_items":"2022-01-25 11:24:12 +0800"},"done":true},"minecraft:story/shiny_gear":{"criteria":{"diamond_boots":"2022-01-25 11:27:12 +0800"},"done":true},"minecraft:recipes/transportation/birch_boat":{"criteria":{"in_water":"2022-01-27 19:47:32 +0800"},"done":true},"minecraft:end/elytra":{"criteria":{"elytra":"2022-01-25 11:23:23 +0800"},"done":true},"minecraft:story/upgrade_tools":{"criteria":{"stone_pickaxe":"2022-01-01 19:51:31 +0800"},"done":true},"minecraft:recipes/decorations/torch":{"criteria":{"has_stone_pickaxe":"2022-01-01 19:51:31 +0800"},"done":true},"minecraft:recipes/transportation/acacia_boat":{"criteria":{"in_water":"2022-01-27 19:47:32 +0800"},"done":true},"minecraft:adventure/totem_of_undying":{"criteria":{"used_totem":"2022-01-25 11:36:57 +0800"},"done":true},"minecraft:recipes/transportation/oak_boat":{"criteria":{"in_water":"2022-01-27 19:47:32 +0800"},"done":true},"minecraft:story/follow_ender_eye":{"criteria":{"in_stronghold":"2022-01-25 11:05:33 +0800"},"done":true},"minecraft:recipes/food/baked_potato_from_campfire_cooking":{"criteria":{"has_potato":"2022-01-25 11:00:48 +0800"},"done":true},"minecraft:adventure/root":{"criteria":{"killed_something":"2022-01-25 11:35:04 +0800"},"done":true},"minecraft:recipes/transportation/jungle_boat":{"criteria":{"in_water":"2022-01-27 19:47:32 +0800"},"done":true},"minecraft:recipes/transportation/spruce_boat":{"criteria":{"in_water":"2022-01-27 19:47:32 +0800"},"done":true},"DataVersion":2865},"data":{"seen":1643286323404,"time_start":1609651831996,"time_last":1643286323404,"time_lived":337561.05000000005,"playername":"Enlerdesu","names":[{"name":"Enlerdesu"}],"uuid_short":"2253dffab3864b0196b481fac176e480","lastUpdate":1643299294198,"uuid":"2253dffa-b386-4b01-96b4-81fac176e480","banned":false}}