{"stats":{"minecraft:picked_up/minecraft:sweet_berries":16,"minecraft:used/minecraft:sweet_berries":16,"minecraft:custom/minecraft:jump":94,"minecraft:custom/minecraft:open_chest":4,"minecraft:custom/minecraft:time_since_rest":73850,"minecraft:custom/minecraft:walk_on_water_one_cm":1377,"minecraft:custom/minecraft:crouch_one_cm":1259,"minecraft:custom/minecraft:play_time":73850,"minecraft:custom/minecraft:leave_game":7,"minecraft:custom/minecraft:sprint_one_cm":31468,"minecraft:custom/minecraft:damage_taken":145,"minecraft:custom/minecraft:time_since_death":73850,"minecraft:custom/minecraft:walk_one_cm":23927,"minecraft:custom/minecraft:sneak_time":155,"minecraft:custom/minecraft:total_world_time":73850,"minecraft:custom/minecraft:walk_under_water_one_cm":874,"minecraft:custom/minecraft:swim_one_cm":3920,"minecraft:custom/minecraft:fall_one_cm":4984,"minecraft:custom/minecraft:fly_one_cm":16182,"minecraft:mined/minecraft:sweet_berry_bush":4},"stats_source":{"stats":{"minecraft:picked_up":{"minecraft:sweet_berries":16},"minecraft:used":{"minecraft:sweet_berries":16},"minecraft:custom":{"minecraft:jump":94,"minecraft:open_chest":4,"minecraft:time_since_rest":73850,"minecraft:walk_on_water_one_cm":1377,"minecraft:crouch_one_cm":1259,"minecraft:play_time":73850,"minecraft:leave_game":7,"minecraft:sprint_one_cm":31468,"minecraft:damage_taken":145,"minecraft:time_since_death":73850,"minecraft:walk_one_cm":23927,"minecraft:sneak_time":155,"minecraft:total_world_time":73850,"minecraft:walk_under_water_one_cm":874,"minecraft:swim_one_cm":3920,"minecraft:fall_one_cm":4984,"minecraft:fly_one_cm":16182},"minecraft:mined":{"minecraft:sweet_berry_bush":4}},"DataVersion":2860},"advancements":{"minecraft:recipes/decorations/torch":{"criteria":{"has_stone_pickaxe":"2021-12-01 21:19:26 +0800"},"done":true},"minecraft:recipes/transportation/acacia_boat":{"criteria":{"in_water":"2021-12-05 17:36:29 +0800"},"done":true},"minecraft:recipes/transportation/oak_boat":{"criteria":{"in_water":"2021-12-05 17:36:29 +0800"},"done":true},"minecraft:husbandry/balanced_diet":{"criteria":{"sweet_berries":"2021-12-05 17:35:11 +0800"},"done":false},"minecraft:recipes/transportation/dark_oak_boat":{"criteria":{"in_water":"2021-12-05 17:36:29 +0800"},"done":true},"minecraft:husbandry/root":{"criteria":{"consumed_item":"2021-12-05 17:35:11 +0800"},"done":true},"minecraft:recipes/transportation/birch_boat":{"criteria":{"in_water":"2021-12-05 17:36:29 +0800"},"done":true},"minecraft:recipes/transportation/jungle_boat":{"criteria":{"in_water":"2021-12-05 17:36:29 +0800"},"done":true},"minecraft:story/upgrade_tools":{"criteria":{"stone_pickaxe":"2021-12-01 21:19:26 +0800"},"done":true},"minecraft:recipes/transportation/spruce_boat":{"criteria":{"in_water":"2021-12-05 17:36:29 +0800"},"done":true},"minecraft:adventure/adventuring_time":{"criteria":{"minecraft:dripstone_caves":"2021-12-05 17:36:53 +0800","minecraft:forest":"2021-12-01 21:19:26 +0800","minecraft:plains":"2021-12-02 20:12:05 +0800"},"done":false},"DataVersion":2860},"data":{"seen":1638697110455,"time_start":1638364766094,"time_last":1638697110455,"time_lived":3692.15,"playername":"Blb2bW4","names":[{"name":"Blb2bW4"}],"uuid_short":"a638992bf2ea3a2798061390de5991fa","lastUpdate":1640712145874,"uuid":"a638992b-f2ea-3a27-9806-1390de5991fa","banned":false}}